Workbook

Sheet Notice
A1: BILAN COMPTABLE DES CAMPAGNES AGRICOLES 2024 ET 2025
A2: Domaine agricole de 60 hectares - Sous-prefecture de Gueasso, Prefecture de Lola, Region de N'Zerekore
A4: 1. IDENTIFICATION DE L'EXPLOITANT
A5: Raison sociale : KASI GROUP SARL (sigle K-G-SARL)
A6: Forme juridique : Societe a responsabilite limitee
A7: RCCM : GN.TCC.2025.B.16465 - Formalite GN.TCC.2025.18612
A8: NIF : 642333652 - Numero eTax : 1228802510892
A9: Date d'immatriculation: 19 novembre 2025, Tribunal de Commerce de Conakry
A10: Capital social : 10 000 000 GNF integralement libere en numeraire
A11: Siege social : Immeuble Sonoco, Marche Niger, Commune de Kaloum, Conakry
A12: Cogerants : KABA Alhassane et SIDIBE Mohamed
A13: Objet social : BTP, commerce, AGRICULTURE, communication, technologie, transport, mines, elevage, immobilier
... A71: Comparatif : synthese de la progression 2024 vers 2025

Sheet Hypotheses
A1: HYPOTHESES TECHNICO-ECONOMIQUES
A2: Toutes les cellules bleues sont modifiables : le classeur entier se recalcule.
A4: A. IDENTIFICATION ET PERIMETRE
A5: Raison sociale de l'exploitant | B5: KASI GROUP SARL
A6: RCCM | B6: GN.TCC.2025.B.16465
A7: NIF | B7: 642333652
A8: Localisation du domaine | B8: Gueasso, Prefecture de Lola, Region de N'Zerekore
A9: Superficie totale du domaine (ha) | B9: 60
A10: Monnaie de tenue des comptes | B10: GNF
A12: B. ASSOLEMENT (hectares emblaves)
A13: Speculation | B13: Campagne 2024 | C13: Campagne 2025 | D13: Variation | E13: Justification
A14: Riz pluvial NERICA | B14: 22 | C14: 23 | D14: =C14-B14 -> 1 | E14: Speculation pivot, debouche local et regional assure
A15: Riz de bas-fond amenage | B15: 0 | C15: 4 | D15: =C15-B15 -> 4 | E15: 4 ha de bas-fond planes et endigues en 2025, rendement double
A16: Mais grain | B16: 14 | C16: 14 | D16: =C16-B16 -> 0 | E16: Rotation et debouche provende / brasserie
A17: Manioc | B17: 12 | C17: 11 | D17: =C17-B17 -> -1 | E17: Surface reduite au profit du riz, plus rentable apres integration de l'usinage
A18: Arachide (coque) | B18: 7 | C18: 6 | D18: =C18-B18 -> -1 | E18: Legumineuse de rotation, fixation azotee, tete d'assolement
A19: Total emblave (ha) | B19: =SUM(B14:B18) -> 55 | C19: =SUM(C14:C18) -> 58 | D19: =C19-B19 -> 3
A20: Superficie non cultivee (siege, hangars, pistes, pare-feu) | B20: =$B$9-B19 -> 5 | C20: =$B$9-C19 -> 2 | D20: =C20-B20 -> -3 | E20: Emprise reduite en 2025 grace au reamenagement des pistes
A22: C. RENDEMENTS (tonnes / hectare)
A23: Speculation | B23: Campagne 2024 | C23: Campagne 2025 | D23: Progression | E23: Justification agronomique
A24: Riz pluvial NERICA | B24: 2.6 | C24: 3.3 | D24: =IF(B24=0,"n.a.",C24/B24-1) -> 0.26923077 | E24: Semence certifiee R1, fumure fractionnee, desherbage precoce
A25: Riz de bas-fond amenage | B25: 0 | C25: 4.5 | D25: =IF(B25=0,"n.a.",C25/B25-1) -> n.a. | E25: Maitrise de l'eau, repiquage en ligne, deux sarclages
A26: Mais grain | B26: 2.9 | C26: 3.7 | D26: =IF(B26=0,"n.a.",C26/B26-1) -> 0.27586207 | E26: Variete composite amelioree, densite 53 000 pieds/ha
A27: Manioc (racines fraiches) | B27: 13.5 | C27: 17 | D27: =IF(B27=0,"n.a.",C27/B27-1) -> 0.25925926 | E27: Boutures saines selectionnees, billonnage mecanise
A28: Arachide (gousses en coque) | B28: 1.35 | C28: 1.7 | D28: =IF(B28=0,"n.a.",C28/B28-1) -> 0.25925926 | E28: Semence renouvelee, traitement de semence, recolte a maturite
A30: D. PARAMETRES TECHNIQUES DE RECOLTE ET DE TRANSFORMATION
A31: Parametre | B31: Campagne 2024 | C31: Campagne 2025 | E31: Commentaire
A32: Taux de pertes post-recolte | B32: 0.1 | C32: 0.05 | E32: 2025 : magasin ventile, sechage sur aire betonnee, palettisation
A33: Rendement a l'usinage du paddy (riz blanc / paddy) | B33: 0.65 | C33: 0.65 | E33: Norme technique d'une decortiqueuse a rouleaux caoutchouc
A34: Rendement de transformation manioc en gari | B34: 0.22 | C34: 0.22 | E34: Norme technique rapeuse-presse (1 t de racines donne 220 kg de gari)
A35: Part du paddy usinee en riz blanc | B35: 0.55 | C35: 0.85 | E35: 2024 : prestation externe limitee. 2025 : unite propre de 1 t/h
A36: Part du manioc transformee en gari | B36: 0.25 | C36: 0.45 | E36: 2025 : rapeuse-presse propre, marge d'usinage internalisee
A38: E. PRIX DE VENTE MOYENS (GNF / kg)
A39: Produit | B39: Campagne 2024 | C39: Campagne 2025 | D39: Variation | E39: Reference de marche
A40: Paddy (riz non usine), bord champ | B40: 5000 | C40: 5400 | D40: =C40/B40-1 -> 0.08 | E40: Marche de collecte de Lola et N'Zerekore
A41: Riz blanc local, sortie magasin | B41: 11500 | C41: 12500 | D41: =C41/B41-1 -> 0.086956522 | E41: Prix de gros N'Zerekore, sac de 50 kg
A42: Mais grain sec | B42: 4200 | C42: 4600 | D42: =C42/B42-1 -> 0.095238095 | E42: Demande provende et brasserie, prix de campagne
A43: Manioc frais (racines) | B43: 1700 | C43: 1850 | D43: =C43/B43-1 -> 0.088235294 | E43: Prix bord champ, vente en vrac aux collecteurs
A44: Gari (semoule de manioc) | B44: 9000 | C44: 10000 | D44: =C44/B44-1 -> 0.11111111 | E44: Prix de detail regional, conditionne en sacs de 25 kg
A45: Arachide en coque | B45: 9500 | C45: 10500 | D45: =C45/B45-1 -> 0.10526316 | E45: Prix de campagne, vente aux huileries et grossistes
A47: F. PARAMETRES FINANCIERS, SOCIAUX ET FISCAUX
A48: Parametre | B48: Campagne 2024 | C48: Campagne 2025 | E48: Commentaire
A49: Taux d'impot sur les benefices | B49: 0.25 | C49: 0.25 | E49: Taux de droit commun, hors regime derogatoire agricole
A50: Taux d'interet emprunt de campagne / moyen terme | B50: 0.14 | C50: 0.14 | E50: Conditions du credit rural en Guinee
A51: Taux d'interet emprunt d'investissement | B51: 0 | C51: 0.13 | E51: Ligne d'investissement 2025, differe de 12 mois
A52: Taux de charges sociales patronales (CNSS) | B52: 0.18 | C52: 0.18 | E52: Cotisation employeur sur salaires bruts
A53: Cout moyen de l'homme-jour (GNF) | B53: 30000 | C53: 32000 | E53: Main-d'oeuvre journaliere locale, repas inclus
A54: Nombre d'hommes-jours de la campagne | B54: 2800 | C54: 3200 | E54: Semis, sarclages, recolte, battage, conditionnement
A55: Taux de change indicatif (GNF / USD) | B55: 8600 | C55: 8700 | E55: Pour conversion et lecture par un partenaire externe
A57: Sources des prix et des rendements : bareme indicatif de campagne des marches de Lola et de N'Zerekore, references techniques ANPROCA / IRAG pour la Guinee forestiere, et estimations de l'exploitant. Ces valeurs sont des hypotheses de travail a valider avant tout engagement.

Sheet Production
A1: PRODUCTION, AFFECTATION ET CHIFFRE D'AFFAIRES
A2: Tonnages en tonnes, valeurs en GNF
A4: 1. PRODUCTION BRUTE ET PRODUCTION COMMERCIALISABLE
A5: Speculation | B5: Surface 2024 (ha) | C5: Rendt 2024 (t/ha) | D5: Prod. brute 2024 (t) | E5: Prod. nette 2024 (t) | F5: Surface 2025 (ha) | G5: Rendt 2025 (t/ha) | H5: Prod. brute 2025 (t) | I5: Prod. nette 2025 (t)
A6: Riz pluvial NERICA | B6: =Hypotheses!B14 -> 22 | C6: =Hypotheses!B24 -> 2.6 | D6: =B6*C6 -> 57.2 | E6: =D6*(1-Hypotheses!$B$32) -> 51.48 | F6: =Hypotheses!C14 -> 23 | G6: =Hypotheses!C24 -> 3.3 | H6: =F6*G6 -> 75.9 | I6: =H6*(1-Hypotheses!$C$32) -> 72.105
A7: Riz de bas-fond amenage | B7: =Hypotheses!B15 -> 0 | C7: =Hypotheses!B25 -> 0 | D7: =B7*C7 -> 0 | E7: =D7*(1-Hypotheses!$B$32) -> 0 | F7: =Hypotheses!C15 -> 4 | G7: =Hypotheses!C25 -> 4.5 | H7: =F7*G7 -> 18 | I7: =H7*(1-Hypotheses!$C$32) -> 17.1
A8: Mais grain | B8: =Hypotheses!B16 -> 14 | C8: =Hypotheses!B26 -> 2.9 | D8: =B8*C8 -> 40.6 | E8: =D8*(1-Hypotheses!$B$32) -> 36.54 | F8: =Hypotheses!C16 -> 14 | G8: =Hypotheses!C26 -> 3.7 | H8: =F8*G8 -> 51.8 | I8: =H8*(1-Hypotheses!$C$32) -> 49.21
A9: Manioc (racines fraiches) | B9: =Hypotheses!B17 -> 12 | C9: =Hypotheses!B27 -> 13.5 | D9: =B9*C9 -> 162 | E9: =D9*(1-Hypotheses!$B$32) -> 145.8 | F9: =Hypotheses!C17 -> 11 | G9: =Hypotheses!C27 -> 17 | H9: =F9*G9 -> 187 | I9: =H9*(1-Hypotheses!$C$32) -> 177.65
A10: Arachide (gousses en coque) | B10: =Hypotheses!B18 -> 7 | C10: =Hypotheses!B28 -> 1.35 | D10: =B10*C10 -> 9.45 | E10: =D10*(1-Hypotheses!$B$32) -> 8.505 | F10: =Hypotheses!C18 -> 6 | G10: =Hypotheses!C28 -> 1.7 | H10: =F10*G10 -> 10.2 | I10: =H10*(1-Hypotheses!$C$32) -> 9.69
A11: Total | B11: =SUM(B6:B10) -> 55 | C11: =SUM(C6:C10) -> 20.35 | D11: =SUM(D6:D10) -> 269.25 | E11: =SUM(E6:E10) -> 242.325 | F11: =SUM(F6:F10) -> 58 | G11: =SUM(G6:G10) -> 30.2 | H11: =SUM(H6:H10) -> 342.9 | I11: =SUM(I6:I10) -> 325.755
A13: 2. AFFECTATION ET VALORISATION DU RIZ
A14: Poste | B14: Campagne 2024 | C14: Campagne 2025 | J14: Commentaire
A15: Paddy net disponible (t) | B15: =E6+E7 -> 51.48 | C15: =I6+I7 -> 89.205 | J15: Somme du riz pluvial et du riz de bas-fond, apres pertes
A16: Paddy dirige vers l'usinage (t) | B16: =B15*Hypotheses!B35 -> 28.314 | C16: =C15*Hypotheses!C35 -> 75.82425 | J16: 2024 : prestation externe. 2025 : decortiqueuse propre
A17: Riz blanc obtenu (t) | B17: =B16*Hypotheses!B33 -> 18.4041 | C17: =C16*Hypotheses!C33 -> 49.285762 | J17: Rendement d'usinage applique au paddy usine
A18: Paddy vendu en l'etat (t) | B18: =B15-B16 -> 23.166 | C18: =C15-C16 -> 13.38075 | J18: Solde vendu brut aux collecteurs
A19: Valeur du riz blanc (GNF) | B19: =B17*Hypotheses!B41*1000 -> 211647150 | C19: =C17*Hypotheses!C41*1000 -> 6.1607203e+08 | J19: Tonnes x prix au kg x 1 000
A20: Valeur du paddy vendu (GNF) | B20: =B18*Hypotheses!B40*1000 -> 115830000 | C20: =C18*Hypotheses!C40*1000 -> 72256050
A21: Chiffre d'affaires riz (GNF) | B21: =B19+B20 -> 327477150 | C21: =C19+C20 -> 6.8832808e+08
A23: 3. AFFECTATION ET VALORISATION DU MANIOC
A24: Poste | B24: Campagne 2024 | C24: Campagne 2025 | J24: Commentaire
A25: Racines nettes disponibles (t) | B25: =E9 -> 145.8 | C25: =I9 -> 177.65
A26: Racines dirigees vers la transformation (t) | B26: =B25*Hypotheses!B36 -> 36.45 | C26: =C25*Hypotheses!C36 -> 79.9425 | J26: 2024 : prestation externe. 2025 : rapeuse-presse propre
A27: Gari obtenu (t) | B27: =B26*Hypotheses!B34 -> 8.019 | C27: =C26*Hypotheses!C34 -> 17.58735
A28: Racines vendues fraiches (t) | B28: =B25-B26 -> 109.35 | C28: =C25-C26 -> 97.7075
A29: Valeur du gari (GNF) | B29: =B27*Hypotheses!B44*1000 -> 72171000 | C29: =C27*Hypotheses!C44*1000 -> 175873500
A30: Valeur des racines fraiches (GNF) | B30: =B28*Hypotheses!B43*1000 -> 185895000 | C30: =C28*Hypotheses!C43*1000 -> 180758875
A31: Chiffre d'affaires manioc (GNF) | B31: =B29+B30 -> 258066000 | C31: =C29+C30 -> 356632375
A33: 4. VALORISATION DU MAIS ET DE L'ARACHIDE
A34: Poste | B34: Campagne 2024 | C34: Campagne 2025 | J34: Commentaire
A35: Mais grain vendu (t) | B35: =E8 -> 36.54 | C35: =I8 -> 49.21
A36: Chiffre d'affaires mais (GNF) | B36: =B35*Hypotheses!B42*1000 -> 153468000 | C36: =C35*Hypotheses!C42*1000 -> 226366000
A37: Arachide en coque vendue (t) | B37: =E10 -> 8.505 | C37: =I10 -> 9.69
A38: Chiffre d'affaires arachide (GNF) | B38: =B37*Hypotheses!B45*1000 -> 80797500 | C38: =C37*Hypotheses!C45*1000 -> 101745000
A40: 5. RECAPITULATIF DES PRODUITS D'EXPLOITATION (GNF)
A41: Compte SYSCOHADA / Nature du produit | B41: Campagne 2024 | C41: Campagne 2025 | D41: Variation | J41: Commentaire
A42: 701 - Ventes de riz (paddy et riz blanc) | B42: =B21 -> 327477150 | C42: =C21 -> 6.8832808e+08 | D42: =IF(B42=0,"n.a.",C42/B42-1) -> 1.1019118
A43: 701 - Ventes de mais grain | B43: =B36 -> 153468000 | C43: =C36 -> 226366000 | D43: =IF(B43=0,"n.a.",C43/B43-1) -> 0.47500456
A44: 701 - Ventes de manioc et de gari | B44: =B31 -> 258066000 | C44: =C31 -> 356632375 | D44: =IF(B44=0,"n.a.",C44/B44-1) -> 0.38194251
A45: 701 - Ventes d'arachide en coque | B45: =B38 -> 80797500 | C45: =C38 -> 101745000 | D45: =IF(B45=0,"n.a.",C45/B45-1) -> 0.25925926
A46: 702 - Ventes de sous-produits (son, brisures, fanes d'arachide) | B46: 14000000 | C46: 28000000 | D46: =IF(B46=0,"n.a.",C46/B46-1) -> 1 | J46: Valorisation des issues de decorticage en aliment du betail
A47: 706 - Prestations de services (decorticage et battage a facon pour tiers) | B47: 0 | C47: 42000000 | D47: =IF(B47=0,"n.a.",C47/B47-1) -> n.a. | J47: L'unite post-recolte acquise en 2025 travaille aussi pour les producteurs voisins
A48: TOTAL DES PRODUITS D'EXPLOITATION | B48: =SUM(B42:B47) -> 833808650 | C48: =SUM(C42:C47) -> 1.4430715e+09 | D48: =C48/B48-1 -> 0.73069859

Sheet Immobilisations
A1: PLAN D'INVESTISSEMENT ET TABLEAU D'AMORTISSEMENT
A2: Amortissement lineaire, calcul prorata temporis a compter de la mise en service
A4: 1. INVESTISSEMENTS DE LA CAMPAGNE 2024
A5: Immobilisation | B5: Valeur d'acquisition (GNF) | C5: Duree (annees) | D5: Mois d'amort. 2024 | E5: Dotation 2024 (GNF) | F5: Dotation 2025 (GNF) | G5: Amort. cumule au 31/12/2025
A6: Amenagement et mise en valeur des terres (defriche, dessouchage, pistes, pare-feu) | B6: 145000000 | C6: 10 | D6: 9 | E6: =B6/C6*D6/12 -> 10875000 | F6: =B6/C6 -> 14500000 | G6: =E6+F6 -> 25375000 | H6: Mise en service avril 2024
A7: Hangar de stockage 150 t et aire de sechage betonnee | B7: 120000000 | C7: 20 | D7: 5 | E7: =B7/C7*D7/12 -> 2500000 | F7: =B7/C7 -> 6000000 | G7: =E7+F7 -> 8500000 | H7: Mise en service aout 2024
A8: Motoculteur et petit materiel agricole | B8: 78000000 | C8: 5 | D8: 10 | E8: =B8/C8*D8/12 -> 13000000 | F8: =B8/C8 -> 15600000 | G8: =E8+F8 -> 28600000 | H8: Mise en service mars 2024
A9: Motopompe et equipement d'irrigation d'appoint | B9: 25000000 | C9: 5 | D9: 8 | E9: =B9/C9*D9/12 -> 3333333.3 | F9: =B9/C9 -> 5000000 | G9: =E9+F9 -> 8333333.3 | H9: Mise en service mai 2024
A10: Tricycle de transport et motocyclettes de service | B10: 62000000 | C10: 5 | D10: 10 | E10: =B10/C10*D10/12 -> 10333333 | F10: =B10/C10 -> 12400000 | G10: =E10+F10 -> 22733333 | H10: Mise en service mars 2024
A11: Mobilier, informatique et installations de bureau | B11: 18000000 | C11: 5 | D11: 10 | E11: =B11/C11*D11/12 -> 3000000 | F11: =B11/C11 -> 3600000 | G11: =E11+F11 -> 6600000 | H11: Mise en service mars 2024
A12: Sous-total investissements 2024 | B12: =SUM(B6:B11) -> 448000000 | E12: =SUM(E6:E11) -> 43041667 | F12: =SUM(F6:F11) -> 57100000 | G12: =SUM(G6:G11) -> 1.0014167e+08
A14: 2. INVESTISSEMENTS DE LA CAMPAGNE 2025
A15: Immobilisation | B15: Valeur d'acquisition (GNF) | C15: Duree (annees) | D15: Mois d'amort. 2025 | E15: Dotation 2024 (GNF) | F15: Dotation 2025 (GNF) | G15: Amort. cumule au 31/12/2025
A16: Tracteur 60 CV et train d'outils (charrue, pulveriseur, remorque) | B16: 385000000 | C16: 8 | D16: 11 | E16: 0 | F16: =B16/C16*D16/12 -> 44114583 | G16: =E16+F16 -> 44114583 | H16: Mise en service fevrier 2025 - fin du recours aux prestataires
A17: Unite post-recolte : decortiqueuse 1 t/h, batteuse, rapeuse-presse a gari | B17: 178000000 | C17: 7 | D17: 10 | E17: 0 | F17: =B17/C17*D17/12 -> 21190476 | G17: =E17+F17 -> 21190476 | H17: Mise en service mars 2025 - internalisation de la marge d'usinage
A18: Extension du hangar et magasin d'intrants securise | B18: 95000000 | C18: 20 | D18: 7 | E18: 0 | F18: =B18/C18*D18/12 -> 2770833.3 | G18: =E18+F18 -> 2770833.3 | H18: Mise en service juin 2025
A19: Amenagement de 4 ha de bas-fond (planage, diguettes, canaux) | B19: 68000000 | C19: 10 | D19: 9 | E19: 0 | F19: =B19/C19*D19/12 -> 5100000 | G19: =E19+F19 -> 5100000 | H19: Mise en service avril 2025 - riziculture a maitrise d'eau
A20: Materiel agricole complementaire et outillage d'atelier | B20: 32000000 | C20: 5 | D20: 8 | E20: 0 | F20: =B20/C20*D20/12 -> 4266666.7 | G20: =E20+F20 -> 4266666.7 | H20: Mise en service mai 2025
A21: Sous-total investissements 2025 | B21: =SUM(B16:B20) -> 758000000 | E21: =SUM(E16:E20) -> 0 | F21: =SUM(F16:F20) -> 77442560 | G21: =SUM(G16:G20) -> 77442560
A23: 3. SYNTHESE DES IMMOBILISATIONS
A24: Poste | B24: Au 31/12/2024 | C24: Au 31/12/2025
A25: Immobilisations brutes | B25: =B12 -> 448000000 | C25: =B12+B21 -> 1206000000
A26: Dotation aux amortissements de l'exercice | B26: =E12+E21 -> 43041667 | C26: =F12+F21 -> 1.3454256e+08
A27: Amortissements cumules | B27: =B26 -> 43041667 | C27: =B26+C26 -> 1.7758423e+08
A28: VALEUR NETTE COMPTABLE | B28: =B25-B27 -> 4.0495833e+08 | C28: =C25-C27 -> 1.0284158e+09
A30: Le financement de ces investissements figure a l'onglet "Flux & Financement". Aucune immobilisation n'est cedee sur la periode : il n'y a donc ni plus-value ni moins-value de cession a constater.

Sheet Charges
A1: CHARGES D'EXPLOITATION DETAILLEES
A2: Classement par compte du plan comptable SYSCOHADA revise - montants en GNF
A4: 60 - ACHATS ET FOURNITURES CONSOMMES
A5: Poste de charge | B5: Campagne 2024 | C5: Campagne 2025 | D5: Variation | E5: Commentaire
A6: 601 - Semences et boutures | B6: 53800000 | C6: 61460000 | D6: =IF(B6=0,"n.a.",C6/B6-1) -> 0.14237918 | E6: 2024 : riz 1 760 kg, mais 350 kg, arachide 700 kg, boutures 12 ha. 2025 : semence certifiee R1
A7: 602 - Engrais mineraux (NPK 15-15-15 et uree) | B7: 106200000 | C7: 131200000 | D7: =IF(B7=0,"n.a.",C7/B7-1) -> 0.2354049 | E7: Riz 200 u. NPK + 100 u. uree/ha ; fumure raisonnee sur analyse de sol en 2025
A8: 602 - Amendements et matiere organique (dolomie, fumure organique) | B8: 0 | C8: 18000000 | D8: =IF(B8=0,"n.a.",C8/B8-1) -> n.a. | E8: Correction de l'acidite des sols ferrallitiques, engage a partir de 2025
A9: 602 - Produits phytosanitaires (herbicides, insecticides, traitement de semence) | B9: =Hypotheses!B19*420000 -> 23100000 | C9: =Hypotheses!C19*450000 -> 26100000 | D9: =IF(B9=0,"n.a.",C9/B9-1) -> 0.12987013 | E9: Cout unitaire par hectare emblave : 420 000 GNF en 2024, 450 000 GNF en 2025
A10: 604 - Emballages (sacs de 50 kg, baches, ficelles, palettes) | B10: 21000000 | C10: 32000000 | D10: =IF(B10=0,"n.a.",C10/B10-1) -> 0.52380952 | E10: Volume conditionne en forte hausse avec l'usinage du riz et le gari
A11: 605 - Carburants et lubrifiants | B11: 34000000 | C11: 96000000 | D11: =IF(B11=0,"n.a.",C11/B11-1) -> 1.8235294 | E11: 2025 : tracteur, unite post-recolte et groupe electrogene en fonctionnement propre
A12: 605 - Pieces de rechange, petit outillage et consommables d'atelier | B12: 16000000 | C12: 38000000 | D12: =IF(B12=0,"n.a.",C12/B12-1) -> 1.375 | E12: Entretien du parc mecanique, en hausse avec l'acquisition du tracteur
A13: Total des achats consommes | B13: =SUM(B6:B12) -> 254100000 | C13: =SUM(C6:C12) -> 402760000
A15: 61 / 62 - TRANSPORTS ET SERVICES EXTERIEURS
A16: Poste de charge | B16: Campagne 2024 | C16: Campagne 2025 | D16: Variation | E16: Commentaire
A17: 61 - Prestations de mecanisation (labour, pulverisage, billonnage) | B17: 48000000 | C17: 14000000 | D17: =IF(B17=0,"n.a.",C17/B17-1) -> -0.70833333 | E17: 2024 : 40 ha travailles par prestataire. 2025 : tracteur propre, prestation residuelle
A18: 61 - Prestation de decorticage du paddy a facon | B18: =Production!B16*700000 -> 19819800 | C18: 0 | D18: =IF(B18=0,"n.a.",C18/B18-1) -> -1 | E18: 700 000 GNF par tonne de paddy usinee ; nul en 2025, decortiqueuse propre
A19: 61 - Prestation de transformation du manioc en gari a facon | B19: =Production!B26*350000 -> 12757500 | C19: 0 | D19: =IF(B19=0,"n.a.",C19/B19-1) -> -1 | E19: 350 000 GNF par tonne de racines ; nul en 2025, rapeuse-presse propre
A20: 61 - Transport, manutention et evacuation vers les marches | B20: 46000000 | C20: 58000000 | D20: =IF(B20=0,"n.a.",C20/B20-1) -> 0.26086957 | E20: Gueasso vers Lola et N'Zerekore, pistes rurales, tonnage evacue en hausse
A21: 62 - Locations et charges locatives diverses | B21: 8000000 | C21: 6000000 | D21: =IF(B21=0,"n.a.",C21/B21-1) -> -0.25
A22: 62 - Primes d'assurance (recolte, materiel, responsabilite civile) | B22: 6000000 | C22: 18000000 | D22: =IF(B22=0,"n.a.",C22/B22-1) -> 2 | E22: 2025 : assurance du tracteur et de l'unite post-recolte, assurance recolte indicielle
A23: 62 - Honoraires (expertise comptable, notaire, conseil juridique et technique) | B23: 10000000 | C23: 16000000 | D23: =IF(B23=0,"n.a.",C23/B23-1) -> 0.6 | E23: 2025 : frais de constitution de la SARL et tenue comptable reguliere
A24: 62 - Telecommunications, energie et fournitures administratives | B24: 12000000 | C24: 22000000 | D24: =IF(B24=0,"n.a.",C24/B24-1) -> 0.83333333
A25: 62 - Formation, vulgarisation et encadrement technique | B25: 0 | C25: 12000000 | D25: =IF(B25=0,"n.a.",C25/B25-1) -> n.a. | E25: Appui-conseil agronomique, itineraires techniques, formation des ouvriers
A26: Total des services exterieurs | B26: =SUM(B17:B25) -> 162577300 | C26: =SUM(C17:C25) -> 146000000
A28: 64 - IMPOTS ET TAXES
A29: Poste de charge | B29: Campagne 2024 | C29: Campagne 2025 | D29: Variation | E29: Commentaire
A30: 64 - Contribution des patentes et licences | B30: 4500000 | C30: 12000000 | D30: =IF(B30=0,"n.a.",C30/B30-1) -> 1.6666667 | E30: 2024 : regime de l'entreprise individuelle. 2025 : patente de la SARL
A31: 64 - Taxes communales, redevances foncieres et coutumieres | B31: 9500000 | C31: 10000000 | D31: =IF(B31=0,"n.a.",C31/B31-1) -> 0.052631579 | E31: Redevances a la commune rurale de Gueasso et aux autorites coutumieres
A32: Total des impots et taxes | B32: =SUM(B30:B31) -> 14000000 | C32: =SUM(C30:C31) -> 22000000
A34: 66 - CHARGES DE PERSONNEL
A35: Poste de charge | B35: Campagne 2024 | C35: Campagne 2025 | D35: Variation | E35: Commentaire
A36: 661 - Direction de l'exploitation (1 poste) | B36: 36000000 | C36: 43200000 | D36: =IF(B36=0,"n.a.",C36/B36-1) -> 0.2 | E36: 2024 : 3 000 000 GNF x 12 mois. 2025 : 3 600 000 GNF x 12 mois
A37: 661 - Techniciens agricoles (2 en 2024, 3 en 2025) | B37: 40800000 | C37: 68400000 | D37: =IF(B37=0,"n.a.",C37/B37-1) -> 0.67647059 | E37: 1 700 000 GNF x 12 x 2 puis 1 900 000 GNF x 12 x 3
A38: 661 - Responsable transformation et commercialisation (1 poste en 2025) | B38: 0 | C38: 26400000 | D38: =IF(B38=0,"n.a.",C38/B38-1) -> n.a. | E38: Poste cree avec l'unite post-recolte : 2 200 000 GNF x 12 mois
A39: 661 - Ouvriers permanents (4 en 2024, 6 en 2025) | B39: 52800000 | C39: 97200000 | D39: =IF(B39=0,"n.a.",C39/B39-1) -> 0.84090909 | E39: 1 200 000 GNF x 11 mois x 4 puis 1 350 000 GNF x 12 mois x 6
A40: 661 - Gardiennage (2 agents) | B40: 24000000 | C40: 26400000 | D40: =IF(B40=0,"n.a.",C40/B40-1) -> 0.1 | E40: Surveillance du domaine, des magasins et du parc materiel
A41: Total des salaires bruts permanents | B41: =SUM(B36:B40) -> 153600000 | C41: =SUM(C36:C40) -> 261600000
A42: 664 - Charges sociales patronales (CNSS) | B42: =B41*Hypotheses!B52 -> 27648000 | C42: =C41*Hypotheses!C52 -> 47088000 | E42: Taux de 18 % applique aux salaires bruts permanents
A43: 662 - Main-d'oeuvre journaliere de campagne | B43: =Hypotheses!B54*Hypotheses!B53 -> 84000000 | C43: =Hypotheses!C54*Hypotheses!C53 -> 102400000 | E43: 2 800 h-j a 30 000 GNF en 2024 ; 3 200 h-j a 32 000 GNF en 2025 (semis, sarclages, recolte)
A44: Total des charges de personnel | B44: =B41+B42+B43 -> 265248000 | C44: =C41+C42+C43 -> 411088000
A46: 67 - CHARGES FINANCIERES
A47: Poste de charge | B47: Campagne 2024 | C47: Campagne 2025 | D47: Variation | E47: Commentaire
A48: Interets sur emprunt de campagne / moyen terme 2024 | B48: =250000000*Hypotheses!B50*10/12 -> 29166667 | C48: =208000000*Hypotheses!C50 -> 29120000 | D48: =IF(B48=0,"n.a.",C48/B48-1) -> -0.0016 | E48: Emprunt de 250 000 000 GNF debloque en mars 2024, 5 ans, taux de 14 %
A49: Interets sur emprunt d'investissement 2025 | B49: 0 | C49: =450000000*Hypotheses!C51*11/12 -> 53625000 | D49: =IF(B49=0,"n.a.",C49/B49-1) -> n.a. | E49: Ligne de 450 000 000 GNF debloquee en fevrier 2025, differe de 12 mois, taux de 13 %
A50: Total des charges financieres | B50: =SUM(B48:B49) -> 29166667 | C50: =SUM(C48:C49) -> 82745000
A52: 68 - DOTATIONS AUX AMORTISSEMENTS
A53: Poste de charge | B53: Campagne 2024 | C53: Campagne 2025 | D53: Variation | E53: Commentaire
A54: 681 - Dotations aux amortissements des immobilisations | B54: =Immobilisations!B26 -> 43041667 | C54: =Immobilisations!C26 -> 1.3454256e+08 | D54: =C54/B54-1 -> 2.1258678 | E54: Report de l'onglet Immobilisations, mode lineaire prorata temporis
A56: RECAPITULATIF GENERAL DES CHARGES
A57: Rubrique | B57: Campagne 2024 | C57: Campagne 2025 | D57: Variation | E57: Poids dans le total 2025
A58: Achats et fournitures consommes | B58: =B13 -> 254100000 | C58: =C13 -> 402760000 | D58: =C58/B58-1 -> 0.58504526 | E58: =C58/C$64 -> 0.33587529
A59: Transports et services exterieurs | B59: =B26 -> 162577300 | C59: =C26 -> 146000000 | D59: =C59/B59-1 -> -0.10196565 | E59: =C59/C$64 -> 0.12175437
A60: Impots et taxes | B60: =B32 -> 14000000 | C60: =C32 -> 22000000 | D60: =C60/B60-1 -> 0.57142857 | E60: =C60/C$64 -> 0.01834655
A61: Charges de personnel | B61: =B44 -> 265248000 | C61: =C44 -> 411088000 | D61: =C61/B61-1 -> 0.54982507 | E61: =C61/C$64 -> 0.34282029
A62: Charges financieres | B62: =B50 -> 29166667 | C62: =C50 -> 82745000 | D62: =C62/B62-1 -> 1.8369714 | E62: =C62/C$64 -> 0.069003875
A63: Dotations aux amortissements | B63: =B54 -> 43041667 | C63: =C54 -> 1.3454256e+08 | D63: =C63/B63-1 -> 2.1258678 | E63: =C63/C$64 -> 0.11219962
A64: TOTAL GENERAL DES CHARGES | B64: =SUM(B58:B63) -> 7.6813363e+08 | C64: =SUM(C58:C63) -> 1.1991356e+09 | D64: =C64/B64-1 -> 0.56110279

Sheet Compte de resultat
A1: COMPTE DE RESULTAT COMPARATIF
A2: Campagnes agricoles 2024 et 2025 - presentation SYSCOHADA - montants en GNF
A4: COMPTE DE RESULTAT DES CAMPAGNES 2024 ET 2025
A5: Libelle | B5: Campagne 2024 | C5: Campagne 2025 | D5: Variation en GNF | E5: Variation en %
A6: PRODUITS D'EXPLOITATION
A7: Ventes de produits agricoles et transformes | B7: =SUM(Production!B42:B45) -> 819808650 | C7: =SUM(Production!C42:C45) -> 1.3730715e+09 | D7: =C7-B7 -> 5.5326281e+08 | E7: =IF(B7=0,"n.a.",C7/B7-1) -> 0.67486822
A8: Ventes de sous-produits | B8: =Production!B46 -> 14000000 | C8: =Production!C46 -> 28000000 | D8: =C8-B8 -> 14000000 | E8: =IF(B8=0,"n.a.",C8/B8-1) -> 1
A9: Prestations de services rendues aux tiers | B9: =Production!B47 -> 0 | C9: =Production!C47 -> 42000000 | D9: =C9-B9 -> 42000000 | E9: =IF(B9=0,"n.a.",C9/B9-1) -> n.a.
A10: Total des produits d'exploitation (I) | B10: =Production!B48 -> 833808650 | C10: =Production!C48 -> 1.4430715e+09 | D10: =C10-B10 -> 6.0926281e+08 | E10: =IF(B10=0,"n.a.",C10/B10-1) -> 0.73069859
A12: CHARGES D'EXPLOITATION
A13: Achats et fournitures consommes | B13: =Charges!B13 -> 254100000 | C13: =Charges!C13 -> 402760000 | D13: =C13-B13 -> 148660000 | E13: =IF(B13=0,"n.a.",C13/B13-1) -> 0.58504526
A14: Transports et services exterieurs | B14: =Charges!B26 -> 162577300 | C14: =Charges!C26 -> 146000000 | D14: =C14-B14 -> -16577300 | E14: =IF(B14=0,"n.a.",C14/B14-1) -> -0.10196565
A15: Impots et taxes | B15: =Charges!B32 -> 14000000 | C15: =Charges!C32 -> 22000000 | D15: =C15-B15 -> 8000000 | E15: =IF(B15=0,"n.a.",C15/B15-1) -> 0.57142857
A16: Charges de personnel | B16: =Charges!B44 -> 265248000 | C16: =Charges!C44 -> 411088000 | D16: =C16-B16 -> 145840000 | E16: =IF(B16=0,"n.a.",C16/B16-1) -> 0.54982507
A17: Dotations aux amortissements | B17: =Charges!B54 -> 43041667 | C17: =Charges!C54 -> 1.3454256e+08 | D17: =C17-B17 -> 91500893 | E17: =IF(B17=0,"n.a.",C17/B17-1) -> 2.1258678
A18: Total des charges d'exploitation (II) | B18: =SUM(B13:B17) -> 7.3896697e+08 | C18: =SUM(C13:C17) -> 1.1163906e+09 | D18: =C18-B18 -> 3.7742359e+08 | E18: =IF(B18=0,"n.a.",C18/B18-1) -> 0.51074488
A20: RESULTAT D'EXPLOITATION (I - II) | B20: =B10-B18 -> 94841683 | C20: =C10-C18 -> 3.266809e+08 | D20: =C20-B20 -> 2.3183921e+08 | E20: =IF(B20=0,"n.a.",C20/B20-1) -> 2.4444865
A22: Charges financieres (III) | B22: =Charges!B50 -> 29166667 | C22: =Charges!C50 -> 82745000 | D22: =C22-B22 -> 53578333 | E22: =IF(B22=0,"n.a.",C22/B22-1) -> 1.8369714
A23: RESULTAT FINANCIER (- III) | B23: =-B22 -> -29166667 | C23: =-C22 -> -82745000 | D23: =C23-B23 -> -53578333 | E23: =IF(B23=0,"n.a.",C23/B23-1) -> 1.8369714
A25: RESULTAT AVANT IMPOT | B25: =B20+B23 -> 65675017 | C25: =C20+C23 -> 2.439359e+08 | D25: =C25-B25 -> 1.7826088e+08 | E25: =IF(B25=0,"n.a.",C25/B25-1) -> 2.7142875
A26: Impot sur les benefices | B26: =MAX(0,B25*Hypotheses!B49) -> 16418754 | C26: =MAX(0,C25*Hypotheses!C49) -> 60983974 | D26: =C26-B26 -> 44565220 | E26: =IF(B26=0,"n.a.",C26/B26-1) -> 2.7142875
A27: RESULTAT NET DE LA CAMPAGNE | B27: =B25-B26 -> 49256262 | C27: =C25-C26 -> 1.8295192e+08 | D27: =C27-B27 -> 1.3369566e+08 | E27: =IF(B27=0,"n.a.",C27/B27-1) -> 2.7142875
A29: Capacite d'autofinancement (resultat net + dotations) | B29: =B27+B17 -> 92297929 | C29: =C27+C17 -> 3.1749448e+08 | D29: =C29-B29 -> 2.2519655e+08 | E29: =IF(B29=0,"n.a.",C29/B29-1) -> 2.4398874
A31: Les deux campagnes degagent un resultat net positif. Le resultat de 2024 est etroit parce que la campagne supporte les couts de premiere installation et une part importante de sous-traitance. En 2025, l'internalisation de la mecanisation et de la transformation, la hausse des rendements et la reduction des pertes post-recolte font plus que compenser l'alourdissement des dotations et des frais financiers lies a l'investissement.

Sheet Flux & Financement
A1: TABLEAU DES FLUX DE TRESORERIE ET PLAN DE FINANCEMENT
A2: Campagnes 2024 et 2025 - montants en GNF
A4: 1. ELEMENTS DU BESOIN EN FONDS DE ROULEMENT
A5: Poste | B5: Au 31/12/2024 | C5: Au 31/12/2025 | D5: Commentaire
A6: Stocks d'intrants et d'emballages | B6: 28000000 | C6: 45000000 | D6: Engrais et semences de la campagne suivante approvisionnes en fin d'annee
A7: Stocks de produits finis (riz, mais, gari en magasin) | B7: 72000000 | C7: 118000000 | D7: Environ 10 % de la production conservee, valorisee au cout de production
A8: Creances clients et autres creances | B8: 46000000 | C8: 78000000 | D8: Ventes a credit court aux grossistes de N'Zerekore et Lola
A9: Dettes fournisseurs | B9: 42000000 | C9: 68000000 | D9: Credit fournisseur sur intrants et transport
A10: Dettes sociales (salaires et CNSS a payer) | B10: 12000000 | C10: 20000000
A11: Dettes fiscales (impot sur les benefices a payer) | B11: ='Compte de resultat'!B26 -> 16418754 | C11: ='Compte de resultat'!C26 -> 60983974 | D11: Impot de l'exercice restant du a la cloture
A12: Besoin en fonds de roulement | B12: =B6+B7+B8-B9-B10-B11 -> 75581246 | C12: =C6+C7+C8-C9-C10-C11 -> 92016026
A13: Variation du besoin en fonds de roulement | B13: =B12-0 -> 75581246 | C13: =C12-B12 -> 16434780
A15: 2. PLAN DE FINANCEMENT
A16: Ressource / Emploi | B16: Campagne 2024 | C16: Campagne 2025 | D16: Commentaire
A17: Apports des promoteurs et comptes courants d'associes | B17: 320000000 | C17: 50000000 | D17: 2024 : 200 000 000 d'apports + 120 000 000 de comptes courants. 2025 : 50 000 000 complementaires
A18: Liberation du capital social de KASI GROUP SARL | B18: 0 | C18: 10000000 | D18: Capital de 10 000 000 GNF integralement libere a la constitution du 19/11/2025
A19: Emprunt de campagne / moyen terme (5 ans, 14 %) | B19: 250000000 | C19: 0 | D19: Debloque en mars 2024 pour l'amenagement et le fonds de roulement
A20: Emprunt d'investissement (7 ans, 13 %, differe de 12 mois) | B20: 0 | C20: 450000000 | D20: Finance le tracteur, l'unite post-recolte et l'amenagement du bas-fond
A21: Remboursement du principal des emprunts | B21: 42000000 | C21: 42000000 | D21: Amortissement du principal de l'emprunt 2024
A22: Encours de l'emprunt moyen terme a la cloture | B22: =B19-B21 -> 208000000 | C22: =B22-C21 -> 166000000
A23: Encours de l'emprunt d'investissement a la cloture | B23: =B20 -> 0 | C23: =B23+C20 -> 450000000
A25: 3. TABLEAU DES FLUX DE TRESORERIE
A26: Flux | B26: Campagne 2024 | C26: Campagne 2025 | D26: Commentaire
A27: Tresorerie a l'ouverture | B27: 0 | C27: =B38 -> 96716683 | D27: Exploitation demarree en 2024, tresorerie initiale nulle
A28: Capacite d'autofinancement | B28: ='Compte de resultat'!B29 -> 92297929 | C28: ='Compte de resultat'!C29 -> 3.1749448e+08 | D28: Resultat net augmente des dotations aux amortissements
A29: Variation du besoin en fonds de roulement | B29: =-B13 -> -75581246 | C29: =-C13 -> -16434780
A30: Flux net de tresorerie d'exploitation | B30: =B28+B29 -> 16716683 | C30: =C28+C29 -> 3.010597e+08
A31: Acquisitions d'immobilisations | B31: =-Immobilisations!B12 -> -448000000 | C31: =-Immobilisations!B21 -> -758000000
A32: Flux net de tresorerie d'investissement | B32: =B31 -> -448000000 | C32: =C31 -> -758000000
A33: Apports et comptes courants d'associes | B33: =B17+B18 -> 320000000 | C33: =C17+C18 -> 60000000
A34: Emprunts nouveaux | B34: =B19+B20 -> 250000000 | C34: =C19+C20 -> 450000000
A35: Remboursement du principal des emprunts | B35: =-B21 -> -42000000 | C35: =-C21 -> -42000000
A36: Flux net de tresorerie de financement | B36: =SUM(B33:B35) -> 528000000 | C36: =SUM(C33:C35) -> 468000000
A37: Variation de tresorerie de la campagne | B37: =B30+B32+B36 -> 96716683 | C37: =C30+C32+C36 -> 11059702
A38: TRESORERIE A LA CLOTURE | B38: =B27+B37 -> 96716683 | C38: =C27+C37 -> 1.0777639e+08 | D38: Disponibilites en banque et en caisse

Sheet Bilan
A1: BILAN COMPARATIF AU 31 DECEMBRE 2024 ET AU 31 DECEMBRE 2025
A2: Presentation SYSCOHADA - montants en GNF
A4: ACTIF
A5: Poste d'actif | B5: Au 31/12/2024 | C5: Au 31/12/2025 | D5: Variation | E5: Commentaire
A6: ACTIF IMMOBILISE
A7: Immobilisations brutes | B7: =Immobilisations!B25 -> 448000000 | C7: =Immobilisations!C25 -> 1206000000 | D7: =C7-B7 -> 758000000
A8: Amortissements cumules (a deduire) | B8: =-Immobilisations!B27 -> -43041667 | C8: =-Immobilisations!C27 -> -1.7758423e+08 | D8: =C8-B8 -> -1.3454256e+08
A9: Total de l'actif immobilise net | B9: =B7+B8 -> 4.0495833e+08 | C9: =C7+C8 -> 1.0284158e+09 | D9: =C9-B9 -> 6.2345744e+08
A10: ACTIF CIRCULANT
A11: Stocks d'intrants et d'emballages | B11: ='Flux & Financement'!B6 -> 28000000 | C11: ='Flux & Financement'!C6 -> 45000000 | D11: =C11-B11 -> 17000000
A12: Stocks de produits finis | B12: ='Flux & Financement'!B7 -> 72000000 | C12: ='Flux & Financement'!C7 -> 118000000 | D12: =C12-B12 -> 46000000
A13: Creances clients et autres creances | B13: ='Flux & Financement'!B8 -> 46000000 | C13: ='Flux & Financement'!C8 -> 78000000 | D13: =C13-B13 -> 32000000
A14: Total de l'actif circulant | B14: =SUM(B11:B13) -> 146000000 | C14: =SUM(C11:C13) -> 241000000 | D14: =C14-B14 -> 95000000
A15: TRESORERIE - ACTIF
A16: Banques, caisse et disponibilites | B16: ='Flux & Financement'!B38 -> 96716683 | C16: ='Flux & Financement'!C38 -> 1.0777639e+08 | D16: =C16-B16 -> 11059702
A17: TOTAL DE L'ACTIF | B17: =B9+B14+B16 -> 6.4767502e+08 | C17: =C9+C14+C16 -> 1.3771922e+09 | D17: =C17-B17 -> 7.2951714e+08
A20: PASSIF
A21: Poste de passif | B21: Au 31/12/2024 | C21: Au 31/12/2025 | D21: Variation | E21: Commentaire
A22: CAPITAUX PROPRES ET RESSOURCES ASSIMILEES
A23: Capital social libere | B23: 0 | C23: ='Flux & Financement'!C18 -> 10000000 | D23: =C23-B23 -> 10000000 | E23: 10 000 000 GNF liberes a la constitution du 19/11/2025
A24: Apports des promoteurs (exploitation en nom propre) | B24: 200000000 | C24: 0 | D24: =C24-B24 -> -200000000 | E24: Reclasses en comptes courants d'associes lors de l'apport a la SARL en 2025
A25: Report a nouveau (resultat de la campagne 2024) | B25: 0 | C25: ='Compte de resultat'!B27 -> 49256262 | D25: =C25-B25 -> 49256262 | E25: Resultat 2024 non distribue, affecte en report a nouveau
A26: Resultat net de la campagne | B26: ='Compte de resultat'!B27 -> 49256262 | C26: ='Compte de resultat'!C27 -> 1.8295192e+08 | D26: =C26-B26 -> 1.3369566e+08
A27: Total des capitaux propres | B27: =SUM(B23:B26) -> 2.4925626e+08 | C27: =SUM(C23:C26) -> 2.4220819e+08 | D27: =C27-B27 -> -7048077.5
A28: Comptes courants d'associes bloques | B28: 120000000 | C28: 370000000 | D28: =C28-B28 -> 250000000 | E28: 2025 : 200 000 000 reclasses + 120 000 000 anterieurs + 50 000 000 nouveaux
A29: Capitaux propres elargis (y compris comptes courants bloques) | B29: =B27+B28 -> 3.6925626e+08 | C29: =C27+C28 -> 6.1220819e+08 | D29: =C29-B29 -> 2.4295192e+08 | E29: Agregat retenu par les bailleurs pour apprecier l'autonomie financiere
A30: DETTES FINANCIERES
A31: Emprunt moyen terme 2024 (encours) | B31: ='Flux & Financement'!B22 -> 208000000 | C31: ='Flux & Financement'!C22 -> 166000000 | D31: =C31-B31 -> -42000000
A32: Emprunt d'investissement 2025 (encours) | B32: ='Flux & Financement'!B23 -> 0 | C32: ='Flux & Financement'!C23 -> 450000000 | D32: =C32-B32 -> 450000000
A33: Total des dettes financieres | B33: =B31+B32 -> 208000000 | C33: =C31+C32 -> 616000000 | D33: =C33-B33 -> 408000000
A34: PASSIF CIRCULANT
A35: Dettes fournisseurs | B35: ='Flux & Financement'!B9 -> 42000000 | C35: ='Flux & Financement'!C9 -> 68000000 | D35: =C35-B35 -> 26000000
A36: Dettes sociales | B36: ='Flux & Financement'!B10 -> 12000000 | C36: ='Flux & Financement'!C10 -> 20000000 | D36: =C36-B36 -> 8000000
A37: Dettes fiscales (impot sur les benefices) | B37: ='Flux & Financement'!B11 -> 16418754 | C37: ='Flux & Financement'!C11 -> 60983974 | D37: =C37-B37 -> 44565220
A38: Total du passif circulant | B38: =SUM(B35:B37) -> 70418754 | C38: =SUM(C35:C37) -> 1.4898397e+08 | D38: =C38-B38 -> 78565220
A39: TOTAL DU PASSIF | B39: =B29+B33+B38 -> 6.4767502e+08 | C39: =C29+C33+C38 -> 1.3771922e+09 | D39: =C39-B39 -> 7.2951714e+08
A42: CONTROLE D'EQUILIBRE DU BILAN
A43: Total de l'actif | B43: =B17 -> 6.4767502e+08 | C43: =C17 -> 1.3771922e+09
A44: Total du passif | B44: =B39 -> 6.4767502e+08 | C44: =C39 -> 1.3771922e+09
A45: Ecart actif - passif (doit etre nul) | B45: =B43-B44 -> 0 | C45: =C43-C44 -> 0
A46: =IF(AND(ABS(B45)<1,ABS(C45)<1),"BILAN EQUILIBRE SUR LES DEUX CAMPAGNES","DESEQUILIBRE - VERIFIER LES SAISIES") -> BILAN EQUILIBRE SUR LES DEUX CAMPAGNES
A48: EQUILIBRE FINANCIER
A49: Indicateur | B49: Au 31/12/2024 | C49: Au 31/12/2025 | E49: Lecture
A50: Ressources stables (capitaux propres elargis + dettes financieres) | B50: =B29+B33 -> 5.7725626e+08 | C50: =C29+C33 -> 1.2282082e+09
A51: Actif immobilise net | B51: =B9 -> 4.0495833e+08 | C51: =C9 -> 1.0284158e+09
A52: Fonds de roulement net global | B52: =B50-B51 -> 1.7229793e+08 | C52: =C50-C51 -> 1.9979241e+08 | E52: Positif : les emplois durables sont finances par des ressources durables
A53: Besoin en fonds de roulement | B53: ='Flux & Financement'!B12 -> 75581246 | C53: ='Flux & Financement'!C12 -> 92016026
A54: Tresorerie nette (fonds de roulement - besoin en fonds de roulement) | B54: =B52-B53 -> 96716683 | C54: =C52-C53 -> 1.0777639e+08 | E54: Doit egaler la tresorerie inscrite a l'actif

Sheet SIG & Ratios
A1: SOLDES INTERMEDIAIRES DE GESTION, RATIOS ET SEUIL DE RENTABILITE
A2: Campagnes 2024 et 2025
A4: 1. SOLDES INTERMEDIAIRES DE GESTION (GNF)
A5: Solde | B5: Campagne 2024 | C5: Campagne 2025 | D5: Variation en % | E5: Definition
A6: Chiffre d'affaires et produits d'exploitation | B6: ='Compte de resultat'!B10 -> 833808650 | C6: ='Compte de resultat'!C10 -> 1.4430715e+09 | D6: =IF(B6=0,"n.a.",C6/B6-1) -> 0.73069859 | E6: Total des ventes, sous-produits et prestations
A7: Consommations intermediaires | B7: ='Compte de resultat'!B13+'Compte de resultat'!B14 -> 416677300 | C7: ='Compte de resultat'!C13+'Compte de resultat'!C14 -> 548760000 | D7: =IF(B7=0,"n.a.",C7/B7-1) -> 0.31699039 | E7: Achats consommes et services exterieurs
A8: VALEUR AJOUTEE | B8: =B6-B7 -> 417131350 | C8: =C6-C7 -> 8.9431146e+08 | D8: =IF(B8=0,"n.a.",C8/B8-1) -> 1.1439565 | E8: Richesse creee par l'exploitation
A9: Impots et taxes | B9: ='Compte de resultat'!B15 -> 14000000 | C9: ='Compte de resultat'!C15 -> 22000000 | D9: =IF(B9=0,"n.a.",C9/B9-1) -> 0.57142857
A10: Charges de personnel | B10: ='Compte de resultat'!B16 -> 265248000 | C10: ='Compte de resultat'!C16 -> 411088000 | D10: =IF(B10=0,"n.a.",C10/B10-1) -> 0.54982507
A11: EXCEDENT BRUT D'EXPLOITATION | B11: =B8-B9-B10 -> 137883350 | C11: =C8-C9-C10 -> 4.6122346e+08 | D11: =IF(B11=0,"n.a.",C11/B11-1) -> 2.3450265 | E11: Performance economique avant amortissements et financement
A12: Dotations aux amortissements | B12: ='Compte de resultat'!B17 -> 43041667 | C12: ='Compte de resultat'!C17 -> 1.3454256e+08 | D12: =IF(B12=0,"n.a.",C12/B12-1) -> 2.1258678
A13: RESULTAT D'EXPLOITATION | B13: =B11-B12 -> 94841683 | C13: =C11-C12 -> 3.266809e+08 | D13: =IF(B13=0,"n.a.",C13/B13-1) -> 2.4444865
A14: Charges financieres | B14: ='Compte de resultat'!B22 -> 29166667 | C14: ='Compte de resultat'!C22 -> 82745000 | D14: =IF(B14=0,"n.a.",C14/B14-1) -> 1.8369714
A15: RESULTAT AVANT IMPOT | B15: =B13-B14 -> 65675017 | C15: =C13-C14 -> 2.439359e+08 | D15: =IF(B15=0,"n.a.",C15/B15-1) -> 2.7142875
A16: Impot sur les benefices | B16: ='Compte de resultat'!B26 -> 16418754 | C16: ='Compte de resultat'!C26 -> 60983974 | D16: =IF(B16=0,"n.a.",C16/B16-1) -> 2.7142875
A17: RESULTAT NET | B17: =B15-B16 -> 49256262 | C17: =C15-C16 -> 1.8295192e+08 | D17: =IF(B17=0,"n.a.",C17/B17-1) -> 2.7142875
A18: CAPACITE D'AUTOFINANCEMENT | B18: =B17+B12 -> 92297929 | C18: =C17+C12 -> 3.1749448e+08 | D18: =IF(B18=0,"n.a.",C18/B18-1) -> 2.4398874 | E18: Resultat net augmente des dotations
A25: 2. RATIOS DE RENTABILITE
A26: Ratio | B26: Campagne 2024 | C26: Campagne 2025 | E26: Lecture
A27: Taux de valeur ajoutee (valeur ajoutee / produits) | B27: =B8/B6 -> 0.50027227 | C27: =C8/C6 -> 0.61972777 | E27: Part de la richesse conservee par l'exploitation
A28: Taux de marge brute d'exploitation (EBE / produits) | B28: =B11/B6 -> 0.1653657 | C28: =C11/C6 -> 0.31961235 | E28: Au-dela de 25 %, l'exploitation est structurellement saine
A29: Taux de marge nette (resultat net / produits) | B29: =B17/B6 -> 0.05907382 | C29: =C17/C6 -> 0.12677953
A30: Rentabilite economique (resultat d'exploitation / total du bilan) | B30: =B13/Bilan!B17 -> 0.14643406 | C30: =C13/Bilan!C17 -> 0.23720793
A31: Rentabilite des capitaux propres elargis (resultat net / capitaux propres elargis) | B31: =B17/Bilan!B29 -> 0.13339317 | C31: =C17/Bilan!C29 -> 0.29883939
A33: 3. RATIOS DE STRUCTURE ET DE SOLVABILITE
A34: Ratio | B34: Au 31/12/2024 | C34: Au 31/12/2025 | E34: Lecture
A35: Autonomie financiere (capitaux propres elargis / total du bilan) | B35: =Bilan!B29/Bilan!B17 -> 0.57012584 | C35: =Bilan!C29/Bilan!C17 -> 0.4445336 | E35: Le repli de 2025 traduit l'effet de levier de l'annee d'investissement, non une degradation
A36: Taux d'endettement financier (dettes financieres / capitaux propres elargis) | B36: =Bilan!B33/Bilan!B29 -> 0.56329444 | C36: =Bilan!C33/Bilan!C29 -> 1.0061937
A37: Capacite de remboursement (dettes financieres / capacite d'autofinancement, en annees) | B37: =Bilan!B33/B18 -> 2.2535717 | C37: =Bilan!C33/C18 -> 1.9401912 | E37: Norme bancaire : moins de 4 annees. Les deux campagnes sont tres en deca
A38: Couverture des frais financiers (EBE / charges financieres) | B38: =B11/B14 -> 4.7274291 | C38: =C11/C14 -> 5.5740342 | E38: Norme : superieur a 3. Marge de securite confortable
A39: Liquidite generale (actif circulant + tresorerie / passif circulant) | B39: =(Bilan!B14+Bilan!B16)/Bilan!B38 -> 3.446762 | C39: =(Bilan!C14+Bilan!C16)/Bilan!C38 -> 2.3410329 | E39: Norme : superieur a 1,5
A41: 4. PERFORMANCE RAMENEE A L'HECTARE (GNF / ha emblave)
A42: Indicateur | B42: Campagne 2024 | C42: Campagne 2025 | D42: Variation en % | E42: Lecture
A43: Superficie emblavee (ha) | B43: =Hypotheses!B19 -> 55 | C43: =Hypotheses!C19 -> 58 | D43: =IF(B43=0,"n.a.",C43/B43-1) -> 0.054545455
A44: Produits d'exploitation par hectare | B44: =B6/B43 -> 15160157 | C44: =C6/C43 -> 24880542 | D44: =IF(B44=0,"n.a.",C44/B44-1) -> 0.6411797
A45: Valeur ajoutee par hectare | B45: =B8/B43 -> 7584206.4 | C45: =C8/C43 -> 15419163 | D45: =IF(B45=0,"n.a.",C45/B45-1) -> 1.0330622 | E45: Indicateur central de la productivite du foncier
A46: Excedent brut d'exploitation par hectare | B46: =B11/B43 -> 2506970 | C46: =C11/C43 -> 7952128.6 | D46: =IF(B46=0,"n.a.",C46/B46-1) -> 2.1720079
A47: Resultat net par hectare | B47: =B17/B43 -> 895568.41 | C47: =C17/C43 -> 3154343.5 | D47: =IF(B47=0,"n.a.",C47/B47-1) -> 2.5221692
A48: Charges d'exploitation par hectare | B48: =(B7+B9+B10+B12)/B43 -> 13435763 | C48: =(C7+C9+C10+C12)/C43 -> 19248113 | D48: =IF(B48=0,"n.a.",C48/B48-1) -> 0.4326029
A50: 5. SEUIL DE RENTABILITE
A51: Element | B51: Campagne 2024 | C51: Campagne 2025 | E51: Methode
A52: Charges fixes (personnel permanent, dotations, frais financiers, impots et taxes, services fixes) | B52: =Charges!B41+Charges!B42+Charges!B54+Charges!B50+Charges!B32+Charges!B21+Charges!B22+Charges!B23+Charges!B24+Charges!B25 -> 3.0345633e+08 | C52: =Charges!C41+Charges!C42+Charges!C54+Charges!C50+Charges!C32+Charges!C21+Charges!C22+Charges!C23+Charges!C24+Charges!C25 -> 6.2197556e+08
A53: Charges variables (charges totales moins charges fixes) | B53: =Charges!B64-B52 -> 464677300 | C53: =Charges!C64-C52 -> 577160000
A54: Marge sur cout variable | B54: =B6-B53 -> 369131350 | C54: =C6-C53 -> 8.6591146e+08
A55: Taux de marge sur cout variable | B55: =B54/B6 -> 0.44270511 | C55: =C54/C6 -> 0.60004753
A56: SEUIL DE RENTABILITE (chiffre d'affaires critique) | B56: =B52/B55 -> 6.854593e+08 | C56: =C52/C55 -> 1.0365438e+09
A57: Seuil de rentabilite en pourcentage des produits | B57: =B56/B6 -> 0.82208226 | C57: =C56/C6 -> 0.71829002 | E57: Plus ce pourcentage est bas, plus l'exploitation resiste a une mauvaise campagne
A58: Marge de securite (produits - seuil de rentabilite) | B58: =B6-B56 -> 1.4834935e+08 | C58: =C6-C56 -> 4.0652763e+08
A60: Les charges fixes retenues comprennent les salaires permanents et les charges sociales, les dotations aux amortissements, les charges financieres, les impots et taxes, ainsi que les services exterieurs non lies au volume (locations, assurances, honoraires, telecommunications, formation). Les intrants, la main-d'oeuvre journaliere, le transport et les prestations a facon sont traites en charges variables.

Sheet Comparatif
A1: SYNTHESE COMPARATIVE DES CAMPAGNES 2024 ET 2025
A2: Deux campagnes beneficiaires, une progression construite sur la technique et la transformation
A4: 1. TABLEAU DE BORD DE LA PROGRESSION
A5: Indicateur | B5: Campagne 2024 | C5: Campagne 2025 | D5: Ecart en GNF | E5: Progression | F5: Facteur explicatif
A6: Superficie emblavee (ha) | B6: =Hypotheses!B19 -> 55 | C6: =Hypotheses!C19 -> 58 | D6: =C6-B6 -> 3 | E6: =IF(B6=0,"n.a.",C6/B6-1) -> 0.054545455 | F6: Mise en valeur de 4 ha de bas-fond et reduction de l'emprise non cultivee
A7: Production totale nette (t) | B7: =Production!E11 -> 242.325 | C7: =Production!I11 -> 325.755 | D7: =C7-B7 -> 83.43 | E7: =IF(B7=0,"n.a.",C7/B7-1) -> 0.34428969 | F7: Rendements en hausse sur toutes les speculations, pertes divisees par deux
A8: Produits d'exploitation | B8: ='SIG & Ratios'!B6 -> 833808650 | C8: ='SIG & Ratios'!C6 -> 1.4430715e+09 | D8: =C8-B8 -> 6.0926281e+08 | E8: =IF(B8=0,"n.a.",C8/B8-1) -> 0.73069859 | F8: Effet combine des volumes, des prix et de la transformation
A9: Valeur ajoutee | B9: ='SIG & Ratios'!B8 -> 417131350 | C9: ='SIG & Ratios'!C8 -> 8.9431146e+08 | D9: =C9-B9 -> 4.7718011e+08 | E9: =IF(B9=0,"n.a.",C9/B9-1) -> 1.1439565 | F9: L'usinage du riz et le gari sont produits en interne au lieu d'etre sous-traites
A10: Excedent brut d'exploitation | B10: ='SIG & Ratios'!B11 -> 137883350 | C10: ='SIG & Ratios'!C11 -> 4.6122346e+08 | D10: =C10-B10 -> 3.2334011e+08 | E10: =IF(B10=0,"n.a.",C10/B10-1) -> 2.3450265 | F10: La masse salariale progresse moins vite que la valeur ajoutee
A11: Resultat d'exploitation | B11: ='SIG & Ratios'!B13 -> 94841683 | C11: ='SIG & Ratios'!C13 -> 3.266809e+08 | D11: =C11-B11 -> 2.3183921e+08 | E11: =IF(B11=0,"n.a.",C11/B11-1) -> 2.4444865
A12: RESULTAT NET DE LA CAMPAGNE | B12: ='SIG & Ratios'!B17 -> 49256262 | C12: ='SIG & Ratios'!C17 -> 1.8295192e+08 | D12: =C12-B12 -> 1.3369566e+08 | E12: =IF(B12=0,"n.a.",C12/B12-1) -> 2.7142875 | F12: Les deux campagnes sont beneficiaires ; 2025 est nettement superieure a 2024
A13: Capacite d'autofinancement | B13: ='SIG & Ratios'!B18 -> 92297929 | C13: ='SIG & Ratios'!C18 -> 3.1749448e+08 | D13: =C13-B13 -> 2.2519655e+08 | E13: =IF(B13=0,"n.a.",C13/B13-1) -> 2.4398874 | F13: Capacite de l'exploitation a financer ses investissements et a rembourser sa dette
A14: Total du bilan | B14: =Bilan!B17 -> 6.4767502e+08 | C14: =Bilan!C17 -> 1.3771922e+09 | D14: =C14-B14 -> 7.2951714e+08 | E14: =IF(B14=0,"n.a.",C14/B14-1) -> 1.126363 | F14: Doublement de l'outil de production
A15: Tresorerie a la cloture | B15: ='Flux & Financement'!B38 -> 96716683 | C15: ='Flux & Financement'!C38 -> 1.0777639e+08 | D15: =C15-B15 -> 11059702 | E15: =IF(B15=0,"n.a.",C15/B15-1) -> 0.11435154 | F15: Tresorerie positive sur les deux campagnes malgre un effort d'investissement lourd
A18: 2. DECOMPOSITION DE L'AMELIORATION DU RESULTAT
A19: Levier | B19: Contribution (GNF) | F19: Explication
A20: Effet volume et rendement (production nette supplementaire) | B20: =(Production!I11-Production!E11)/Production!I11*('SIG & Ratios'!C6-'SIG & Ratios'!B6) -> 1.5603996e+08 | F20: Hausse des rendements de toutes les speculations et reduction des pertes de 10 % a 5 %
A21: Effet prix et transformation (valorisation unitaire supplementaire) | B21: ='SIG & Ratios'!C6-'SIG & Ratios'!B6-B20 -> 4.5322285e+08 | F21: Usinage de 85 % du paddy contre 55 %, gari sur 45 % du manioc contre 25 %, prix en hausse
A22: Total de l'augmentation des produits | B22: =B20+B21 -> 6.0926281e+08
A23: Augmentation des charges d'exploitation et financieres | B23: =-(Charges!C64-Charges!B64) -> -4.3100193e+08 | F23: Investissement, personnel renforce, dotations et frais financiers en hausse
A24: Augmentation de l'impot sur les benefices | B24: =-('Compte de resultat'!C26-'Compte de resultat'!B26) -> -44565220
A25: AMELIORATION NETTE DU RESULTAT | B25: =B22+B23+B24 -> 1.3369566e+08 | F25: Ecart entre le resultat net 2025 et le resultat net 2024
A26: Controle : resultat net 2025 moins resultat net 2024 | B26: ='SIG & Ratios'!C17-'SIG & Ratios'!B17 -> 1.3369566e+08
A27: =IF(ABS(B25-B26)<1,"DECOMPOSITION COHERENTE","ECART A VERIFIER") -> DECOMPOSITION COHERENTE
A29: 3. CONCLUSION
A30: - Les deux campagnes se soldent par un resultat net positif, ce qui etait l'objectif de la mise en valeur du domaine de 60 hectares de Gueasso.
A33: - La campagne 2024 est beneficiaire mais etroite : elle supporte la defriche, l'amenagement initial, une mecanisation entierement sous-traitee et des pertes post-recolte de 10 %. Le seuil de rentabilite y est atteint tard dans la campagne, ce qui laisse peu de marge de securite.
A36: - La campagne 2025 change d'echelle sans changer de surface. Trois leviers expliquent la progression : des rendements superieurs grace aux semences certifiees et a la fumure raisonnee, la mise en valeur de 4 hectares de bas-fond rizicole a maitrise d'eau, et surtout l'internalisation de la transformation qui fait passer la part du paddy usine de 55 % a 85 % et celle du manioc transforme en gari de 25 % a 45 %.
A39: - L'investissement de 2025 alourdit mecaniquement les dotations aux amortissements et les charges financieres. Cet alourdissement est plus que compense par la marge d'usinage captee en interne : la valeur ajoutee par hectare double.
A42: - La structure financiere reste saine sur les deux campagnes : la tresorerie est positive a chaque cloture, le fonds de roulement couvre le besoin en fonds de roulement, et la capacite de remboursement demeure tres en deca de la norme bancaire de quatre annees.
A45: - Points de vigilance a documenter avant tout engagement : la volatilite des prix du paddy et du manioc, l'irregularite pluviometrique, l'etat des pistes rurales entre Gueasso et N'Zerekore pour l'evacuation des recoltes, et la disponibilite effective de la main-d'oeuvre journaliere aux pics de travaux.
